gitrecovery/__init__.py
gitrecovery/recover.py
gitrecovery1-1.0.0.dist-info/LICENSE
gitrecovery1-1.0.0.dist-info/METADATA
gitrecovery1-1.0.0.dist-info/WHEEL
gitrecovery1-1.0.0.dist-info/top_level.txt
gitrecovery1-1.0.0.dist-info/RECORD
